[{"timestamp":1555623796335,"event":"shippy_become_client_begin","source":1555623795194},{"timestamp":1555623796336,"event":"shippy_become_client_end","source":null},{"timestamp":1555623796400,"event":"shippy_client_received_welcome","source":1555623796392,"from":1555623795194,"pkgSize":26},{"timestamp":1555623796401,"event":"shippy_client_received_stateupdate","source":1555623796392,"pkgSize":148,"numSuccessors":2,"isBroadcast":true,"version":42,"tempID":1555623795194},{"timestamp":1555623798087,"event":"shippy_client_received_stateupdate","source":1555623796392,"pkgSize":162,"numSuccessors":3,"isBroadcast":true,"version":42,"tempID":1555623795194},{"timestamp":1555623799338,"event":"shippy_client_received_stateupdate","source":1555623796392,"pkgSize":176,"numSuccessors":4,"isBroadcast":true,"version":42,"tempID":1555623795194},{"timestamp":1555623801393,"event":"shippy_client_received_stateupdate","source":1555623796392,"pkgSize":190,"numSuccessors":5,"isBroadcast":true,"version":42,"tempID":1555623795194},{"timestamp":1555623803564,"event":"shippy_client_received_stateupdate","source":1555623796392,"pkgSize":148,"numSuccessors":5,"isBroadcast":false,"version":43,"tempID":1555623795194},{"timestamp":1555623805061,"event":"shippy_client_received_stateupdate","source":1555623796392,"pkgSize":343,"numSuccessors":5,"isBroadcast":false,"version":44,"tempID":1555623795194},{"timestamp":1555623806916,"event":"shippy_client_received_stateupdate","source":1555623796392,"pkgSize":340,"numSuccessors":5,"isBroadcast":false,"version":45,"tempID":1555623795194},{"timestamp":1555623808529,"event":"shippy_client_received_stateupdate","source":1555623796392,"pkgSize":4183,"numSuccessors":5,"isBroadcast":false,"version":46,"tempID":1555623795194},{"timestamp":1555623809955,"event":"shippy_client_received_stateupdate","source":1555623796392,"pkgSize":148,"numSuccessors":5,"isBroadcast":false,"version":47,"tempID":1555623795194},{"timestamp":1555623811079,"event":"shippy_client_received_stateupdate","source":1555623796392,"pkgSize":343,"numSuccessors":5,"isBroadcast":false,"version":48,"tempID":1555623795194},{"timestamp":1555623812261,"event":"shippy_client_received_stateupdate","source":1555623796392,"pkgSize":148,"numSuccessors":5,"isBroadcast":false,"version":49,"tempID":1555623795194},{"timestamp":1555623819959,"event":"shippy_become_client_begin","source":1555623795194},{"timestamp":1555623819959,"event":"shippy_become_client_end","source":1555623796392},{"timestamp":1555623820000,"event":"shippy_client_received_welcome","source":1555623819998,"from":1555623795194,"pkgSize":26},{"timestamp":1555623820004,"event":"shippy_client_received_stateupdate","source":1555623819998,"pkgSize":148,"numSuccessors":2,"isBroadcast":true,"version":49,"tempID":1555623795194},{"timestamp":1555623820030,"event":"shippy_client_received_stateupdate","source":1555623819998,"pkgSize":162,"numSuccessors":3,"isBroadcast":true,"version":49,"tempID":1555623795194},{"timestamp":1555623820041,"event":"shippy_client_received_stateupdate","source":1555623819998,"pkgSize":176,"numSuccessors":4,"isBroadcast":true,"version":49,"tempID":1555623795194},{"timestamp":1555623822174,"event":"shippy_client_received_stateupdate","source":1555623819998,"pkgSize":90,"numSuccessors":4,"isBroadcast":false,"version":50,"tempID":1555623795194},{"timestamp":1555623824175,"event":"shippy_client_received_stateupdate","source":1555623819998,"pkgSize":156,"numSuccessors":4,"isBroadcast":false,"version":51,"tempID":1555623795194},{"timestamp":1555623826086,"event":"shippy_client_received_stateupdate","source":1555623819998,"pkgSize":345,"numSuccessors":4,"isBroadcast":false,"version":52,"tempID":1555623795194},{"timestamp":1555623827369,"event":"shippy_client_received_stateupdate","source":1555623819998,"pkgSize":108,"numSuccessors":4,"isBroadcast":false,"version":53,"tempID":1555623795194},{"timestamp":1555623828934,"event":"shippy_client_received_stateupdate","source":1555623819998,"pkgSize":90,"numSuccessors":4,"isBroadcast":false,"version":54,"tempID":1555623795194},{"timestamp":1555623829800,"event":"shippy_client_received_stateupdate","source":1555623819998,"pkgSize":93,"numSuccessors":4,"isBroadcast":false,"version":55,"tempID":1555623795194},{"timestamp":1555623831085,"event":"shippy_client_received_stateupdate","source":1555623819998,"pkgSize":105,"numSuccessors":4,"isBroadcast":false,"version":56,"tempID":1555623795194},{"timestamp":1555623832308,"event":"shippy_client_received_stateupdate","source":1555623819998,"pkgSize":156,"numSuccessors":4,"isBroadcast":false,"version":57,"tempID":1555623795194},{"timestamp":1555623833388,"event":"shippy_client_received_stateupdate","source":1555623819998,"pkgSize":90,"numSuccessors":4,"isBroadcast":false,"version":58,"tempID":1555623795194},{"timestamp":1555623840010,"event":"shippy_become_client_begin","source":1555623795194},{"timestamp":1555623840011,"event":"shippy_become_client_end","source":1555623819998},{"timestamp":1555623840026,"event":"shippy_client_received_welcome","source":1555623840024,"from":1555623795194,"pkgSize":26},{"timestamp":1555623840027,"event":"shippy_client_received_stateupdate","source":1555623840024,"pkgSize":134,"numSuccessors":1,"isBroadcast":true,"version":58,"tempID":1555623795194},{"timestamp":1555623840044,"event":"shippy_client_received_stateupdate","source":1555623840024,"pkgSize":148,"numSuccessors":2,"isBroadcast":true,"version":58,"tempID":1555623795194},{"timestamp":1555623840053,"event":"shippy_client_received_stateupdate","source":1555623840024,"pkgSize":162,"numSuccessors":3,"isBroadcast":true,"version":58,"tempID":1555623795194},{"timestamp":1555623840060,"event":"shippy_client_received_stateupdate","source":1555623840024,"pkgSize":148,"numSuccessors":2,"isBroadcast":true,"version":58,"tempID":1555623795194},{"timestamp":1555623840062,"event":"shippy_client_received_stateupdate","source":1555623840024,"pkgSize":148,"numSuccessors":2,"isBroadcast":true,"version":58,"tempID":1555623795194},{"timestamp":1555623840073,"event":"shippy_client_received_stateupdate","source":1555623840024,"pkgSize":162,"numSuccessors":3,"isBroadcast":true,"version":58,"tempID":1555623795194},{"timestamp":1555623843325,"event":"shippy_client_received_stateupdate","source":1555623840024,"pkgSize":152,"numSuccessors":3,"isBroadcast":false,"version":59,"tempID":1555623795194},{"timestamp":1555623845122,"event":"shippy_client_received_stateupdate","source":1555623840024,"pkgSize":1115,"numSuccessors":3,"isBroadcast":false,"version":60,"tempID":1555623795194},{"timestamp":1555623846549,"event":"shippy_client_received_stateupdate","source":1555623840024,"pkgSize":89,"numSuccessors":3,"isBroadcast":false,"version":61,"tempID":1555623795194},{"timestamp":1555623847923,"event":"shippy_client_received_stateupdate","source":1555623840024,"pkgSize":92,"numSuccessors":3,"isBroadcast":false,"version":62,"tempID":1555623795194},{"timestamp":1555623849385,"event":"shippy_client_received_stateupdate","source":1555623840024,"pkgSize":344,"numSuccessors":3,"isBroadcast":false,"version":63,"tempID":1555623795194},{"timestamp":1555623851319,"event":"shippy_client_received_stateupdate","source":1555623840024,"pkgSize":107,"numSuccessors":3,"isBroadcast":false,"version":64,"tempID":1555623795194},{"timestamp":1555623853119,"event":"shippy_client_received_stateupdate","source":1555623840024,"pkgSize":104,"numSuccessors":3,"isBroadcast":false,"version":65,"tempID":1555623795194},{"timestamp":1555623854426,"event":"shippy_client_received_stateupdate","source":1555623840024,"pkgSize":1115,"numSuccessors":3,"isBroadcast":false,"version":66,"tempID":1555623795194},{"timestamp":1555623855674,"event":"shippy_client_received_stateupdate","source":1555623840024,"pkgSize":344,"numSuccessors":3,"isBroadcast":false,"version":67,"tempID":1555623795194},{"timestamp":1555623858061,"event":"shippy_become_server_begin","source":1555623840024},{"timestamp":1555623858067,"event":"shippy_become_server_end","source":1555623840024},{"timestamp":1555623860071,"event":"shippy_become_client_begin","source":1555623795194},{"timestamp":1555623860072,"event":"shippy_become_client_end","source":1555623840024},{"timestamp":1555623860085,"event":"shippy_server_ws_open","source":1555623840024,"from":1555623860085},{"timestamp":1555623860087,"event":"shippy_client_received_welcome","source":1555623860085,"from":1555623795194,"pkgSize":26},{"timestamp":1555623860089,"event":"shippy_server_received__revealdoublerole","source":1555623860085,"from":1555623860085,"pkgSize":63},{"timestamp":1555623860110,"event":"shippy_server_ws_open","source":1555623860085,"from":1555623860110},{"timestamp":1555623860121,"event":"shippy_server_ws_open","source":1555623860085,"from":1555623860121},{"timestamp":1555623862444,"event":"shippy_client_call_add","source":1555623860085,"version":67},{"timestamp":1555623862445,"event":"shippy_server_received_add","source":1555623860085,"from":1555623860085,"pkgSize":1074},{"timestamp":1555623863692,"event":"shippy_client_call_remove","source":1555623860085,"version":68},{"timestamp":1555623863693,"event":"shippy_server_received_remove","source":1555623860085,"from":1555623860085,"pkgSize":117},{"timestamp":1555623864929,"event":"shippy_client_call_add","source":1555623860085,"version":69},{"timestamp":1555623864931,"event":"shippy_server_received_add","source":1555623860085,"from":1555623860085,"pkgSize":114},{"timestamp":1555623866031,"event":"shippy_client_call_remove","source":1555623860085,"version":70},{"timestamp":1555623866034,"event":"shippy_server_received_remove","source":1555623860085,"from":1555623860085,"pkgSize":1077},{"timestamp":1555623867280,"event":"shippy_client_call_add","source":1555623860085,"version":71},{"timestamp":1555623867282,"event":"shippy_server_received_add","source":1555623860085,"from":1555623860085,"pkgSize":306},{"timestamp":1555623868417,"event":"shippy_client_call_remove","source":1555623860085,"version":72},{"timestamp":1555623868418,"event":"shippy_server_received_remove","source":1555623860085,"from":1555623860085,"pkgSize":54},{"timestamp":1555623869665,"event":"shippy_client_call_add","source":1555623860085,"version":73},{"timestamp":1555623869666,"event":"shippy_server_received_add","source":1555623860085,"from":1555623860085,"pkgSize":1074},{"timestamp":1555623871970,"event":"disconnecting","source":1555623860085,"isServer":true}]